setup.py
batcher/__init__.py
batcher/batcher.py
batcher/tests.py
python_batcher.egg-info/PKG-INFO
python_batcher.egg-info/SOURCES.txt
python_batcher.egg-info/dependency_links.txt
python_batcher.egg-info/namespace_packages.txt
python_batcher.egg-info/not-zip-safe
python_batcher.egg-info/top_level.txt